gcm/__init__.py
gcm/cli.py
gcm/commands/__init__.py
gcm/commands/base.py
gcm/commands/clear.py
gcm/commands/context.py
gcm/commands/disable.py
gcm/commands/enable.py
gcm/commands/exit_codes.py
gcm/commands/stats.py
gcm/commands/validators.py
gcm/utils.py
gentoo_cache_manager-0.2.1.dist-info/METADATA
gentoo_cache_manager-0.2.1.dist-info/WHEEL
gentoo_cache_manager-0.2.1.dist-info/entry_points.txt
gentoo_cache_manager-0.2.1.dist-info/licenses/LICENSE
gentoo_cache_manager-0.2.1.dist-info/RECORD
