Metadata-Version: 2.1
Name: gentoo-cache-manager
Version: 0.2.1
Summary: 🗃️ Helps tweaking build cache settings for individual packages
Keywords: gentoo,cache,manager,ccache
Author-Email: Aliaksei Urbanski <aliaksei.urbanski@gmail.com>
Maintainer-Email: Aliaksei Urbanski <aliaksei.urbanski@gmail.com>
License: MIT
Classifier: License :: OSI Approved :: MIT License
Classifier: Development Status :: 4 - Beta
Classifier: Environment :: Console
Classifier: Intended Audience :: Developers
Classifier: Intended Audience :: System Administrators
Classifier: Topic :: Software Development
Classifier: Topic :: System :: Installation/Setup
Classifier: Topic :: System :: Systems Administration
Classifier: Topic :: Utilities
Classifier: Programming Language :: Python
Classifier: Programming Language :: Python :: 3.11
Classifier: Programming Language :: Python :: 3.12
Classifier: Programming Language :: Python :: 3.13
Classifier: Programming Language :: Python :: 3.14
Classifier: Programming Language :: Python :: Implementation :: CPython
Project-URL: Repository, https://github.com/Jamim/gentoo-cache-manager
Project-URL: Issues, https://github.com/Jamim/gentoo-cache-manager/issues
Requires-Python: >=3.11
Requires-Dist: click<8.1.8
Requires-Dist: portage
